django_taskflow/__init__.py
django_taskflow/admin.py
django_taskflow/apps.py
django_taskflow/models.py
django_taskflow/tests.py
django_taskflow/version.py
django_taskflow/views.py
django_taskflow/migrations/__init__.py
django_taskflow-0.0.1.dist-info/LICENSE
django_taskflow-0.0.1.dist-info/METADATA
django_taskflow-0.0.1.dist-info/WHEEL
django_taskflow-0.0.1.dist-info/top_level.txt
django_taskflow-0.0.1.dist-info/RECORD
